{
  "$schema": "https://mintlify.com/docs.json",
  "name": "Z3 Theorem Prover",
  "theme": "aspen",
  "colors": {
    "primary": "#646464",
    "light": "#d39a13",
    "dark": "#f9f9f4"
  },
  "favicon": "https://media.brand.dev/8c9d4127-f22f-4fd3-9a96-421c72c937e9.png",
  "logo": {
    "light": "https://media.brand.dev/c094bf67-3a01-4f4d-b18d-a09b69f78ac0.png",
    "dark": "https://media.brand.dev/c094bf67-3a01-4f4d-b18d-a09b69f78ac0.png"
  },
  "navbar": {
    "primary": {
      "type": "github",
      "href": "https://github.com/Z3Prover/z3"
    }
  },
  "footer": {
    "socials": {
      "github": "https://github.com/Z3Prover/z3"
    }
  },
  "navigation": {
    "tabs": [
      {
        "tab": "Documentation",
        "groups": [
          {
            "group": "Getting Started",
            "pages": [
              "introduction",
              "quickstart",
              "installation"
            ]
          },
          {
            "group": "Core Concepts",
            "pages": [
              "concepts/smt-solving",
              "concepts/expressions",
              "concepts/solvers",
              "concepts/tactics",
              "concepts/models",
              "concepts/quantifiers"
            ]
          },
          {
            "group": "Building Z3",
            "pages": [
              "building/cmake",
              "building/make",
              "building/visual-studio",
              "building/bazel"
            ]
          },
          {
            "group": "Guides",
            "pages": [
              "guides/optimization",
              "guides/fixedpoint",
              "guides/floating-point",
              "guides/finite-sets",
              "guides/sequences-strings"
            ]
          }
        ]
      },
      {
        "tab": "Language Bindings",
        "groups": [
          {
            "group": "Python",
            "pages": [
              "bindings/python/installation",
              "bindings/python/getting-started",
              "bindings/python/api-reference"
            ]
          },
          {
            "group": "C++",
            "pages": [
              "bindings/cpp/installation",
              "bindings/cpp/getting-started",
              "bindings/cpp/api-reference"
            ]
          },
          {
            "group": "C",
            "pages": [
              "bindings/c/installation",
              "bindings/c/getting-started",
              "bindings/c/api-reference"
            ]
          },
          {
            "group": "Java",
            "pages": [
              "bindings/java/installation",
              "bindings/java/getting-started",
              "bindings/java/api-reference"
            ]
          },
          {
            "group": ".NET",
            "pages": [
              "bindings/dotnet/installation",
              "bindings/dotnet/getting-started",
              "bindings/dotnet/api-reference"
            ]
          },
          {
            "group": "JavaScript/TypeScript",
            "pages": [
              "bindings/javascript/installation",
              "bindings/javascript/getting-started",
              "bindings/javascript/api-reference"
            ]
          },
          {
            "group": "Go",
            "pages": [
              "bindings/go/installation",
              "bindings/go/getting-started",
              "bindings/go/api-reference"
            ]
          },
          {
            "group": "OCaml",
            "pages": [
              "bindings/ocaml/installation",
              "bindings/ocaml/getting-started"
            ]
          }
        ]
      },
      {
        "tab": "API Reference",
        "groups": [
          {
            "group": "Core API",
            "pages": [
              "api/context",
              "api/expressions",
              "api/sorts",
              "api/solver",
              "api/model",
              "api/tactics",
              "api/optimize",
              "api/fixedpoint"
            ]
          },
          {
            "group": "Theory Solvers",
            "pages": [
              "api/theories/arithmetic",
              "api/theories/bitvectors",
              "api/theories/arrays",
              "api/theories/datatypes",
              "api/theories/floating-point",
              "api/theories/sequences",
              "api/theories/finite-sets"
            ]
          },
          {
            "group": "Advanced",
            "pages": [
              "api/advanced/parameters",
              "api/advanced/statistics",
              "api/advanced/proofs",
              "api/advanced/simplifiers"
            ]
          }
        ]
      },
      {
        "tab": "Examples",
        "groups": [
          {
            "group": "Tutorials",
            "pages": [
              "examples/basic-solving",
              "examples/sudoku-solver",
              "examples/optimization-problems",
              "examples/program-verification"
            ]
          },
          {
            "group": "Use Cases",
            "pages": [
              "examples/constraint-solving",
              "examples/model-checking",
              "examples/automated-testing",
              "examples/symbolic-execution"
            ]
          }
        ]
      }
    ]
  }
}
